tests/__init__.py
tests/test_varys.py
varys/__init__.py
varys/consumer.py
varys/controller.py
varys/process.py
varys/producer.py
varys/utils.py
varys_client-1.2.0.dist-info/licenses/LICENSE
varys_client-1.2.0.dist-info/METADATA
varys_client-1.2.0.dist-info/WHEEL
varys_client-1.2.0.dist-info/top_level.txt
varys_client-1.2.0.dist-info/RECORD
