Metadata-Version: 2.4
Name: varys-client
Version: 1.2.0
Summary: A pika-based python RabbitMQ client for use in the CLIMB-GRE project
Home-page: https://github.com/climb-tre/varys
Author: Sam Wilkinson
Author-email: s.a.j.wilkinson@bham.ac.uk
License: GNU GPLv3
Classifier: Programming Language :: Python :: 3
Requires-Python: >=3.7
License-File: LICENSE
Requires-Dist: pika>=1.3.0
Requires-Dist: setuptools>=42
Dynamic: license-file
